synformer/__init__.py
synformer/version.py
synformer/chem/__init__.py
synformer/chem/base.py
synformer/chem/featurize.py
synformer/chem/fpindex.py
synformer/chem/matrix.py
synformer/chem/mol.py
synformer/chem/reaction.py
synformer/chem/stack.py
synformer/data/__init__.py
synformer/data/collate.py
synformer/data/common.py
synformer/data/projection_dataset.py
synformer/data/projection_dataset_new.py
synformer/models/__init__.py
synformer/models/classifier_head.py
synformer/models/decoder.py
synformer/models/diffusion.py
synformer/models/synformer.py
synformer/models/wrapper.py
synformer/models/encoder/__init__.py
synformer/models/encoder/base.py
synformer/models/encoder/discrete.py
synformer/models/encoder/fixed.py
synformer/models/encoder/graph.py
synformer/models/encoder/smiles.py
synformer/models/fingerprint_head/__init__.py
synformer/models/fingerprint_head/ar.py
synformer/models/fingerprint_head/base.py
synformer/models/fingerprint_head/diffusion.py
synformer/models/fingerprint_head/multi.py
synformer/models/projector/__init__.py
synformer/models/projector/base.py
synformer/models/projector/diffusion.py
synformer/models/projector/diffusion_bernoulli.py
synformer/models/projector/diffusion_bernoulli_smiles.py
synformer/models/projector/vanilla.py
synformer/models/projector/wrapper.py
synformer/models/quantizer/__init__.py
synformer/models/quantizer/lfq.py
synformer/models/transformer/__init__.py
synformer/models/transformer/gradient_checkpointing.py
synformer/models/transformer/graph_transformer.py
synformer/models/transformer/positional_encoding.py
synformer/models/transformer/rotary_embedding.py
synformer/molopt/__init__.py
synformer/molopt/__main__.py
synformer/molopt/model.py
synformer/molopt/oracle.py
synformer/molopt/replay.py
synformer/molopt_old/__init__.py
synformer/molopt_old/__main__.py
synformer/sampler/__init__.py
synformer/sampler/analog/__init__.py
synformer/sampler/analog/cli.py
synformer/sampler/analog/parallel.py
synformer-0.1.3.dist-info/LICENSE
synformer-0.1.3.dist-info/METADATA
synformer-0.1.3.dist-info/WHEEL
synformer-0.1.3.dist-info/top_level.txt
synformer-0.1.3.dist-info/RECORD
