Metadata-Version: 2.1
Name: synformer
Version: 0.1.3
Summary: SynFormer: Generative Model for Synthesizable Molecule Generation
Author-email: Wenhao Gao <gaowh19@gmail.com>, Shitong Luo <luost26@gmail.com>, "Connor W. Coley" <ccoley@mit.edu>
License: Apache License
Requires-Python: >=3.10
License-File: LICENSE
Requires-Dist: rdkit>=2023.09
Requires-Dist: torch>=2.0
Requires-Dist: pytorch-lightning>=2.0
Requires-Dist: tensorboard
Requires-Dist: einops
Requires-Dist: scikit-learn
Requires-Dist: numpy
Requires-Dist: pandas
Requires-Dist: pyyaml
Requires-Dist: types-pyyaml
Requires-Dist: joblib
Requires-Dist: omegaconf
Requires-Dist: gitpython
Requires-Dist: cryptography
Requires-Dist: rich
Requires-Dist: matplotlib
Requires-Dist: seaborn
Requires-Dist: tqdm
Requires-Dist: jupyterlab
Requires-Dist: ipywidgets
Requires-Dist: click
